README.md
setup.py
py_mcpe_stats/__init__.py
py_mcpe_stats/_server_data.py
py_mcpe_stats/query.py
py_mcpe_stats.egg-info/PKG-INFO
py_mcpe_stats.egg-info/SOURCES.txt
py_mcpe_stats.egg-info/dependency_links.txt
py_mcpe_stats.egg-info/top_level.txt
py_mcpe_stats/_raknet/__init__.py
py_mcpe_stats/_raknet/rak_lib.py
py_mcpe_stats/_raknet/packet/__init__.py
py_mcpe_stats/_raknet/packet/packet.py
py_mcpe_stats/_raknet/packet/unconnected_ping.py
py_mcpe_stats/_raknet/packet/unconnected_pong.py